{"cameraMode":{"drawMode":0,"name":"Shaded","section":"Shading Mode"},"sceneLighting":true,"audioPlay":false,"sceneViewState":{"m_AlwaysRefresh":false,"showFog":true,"showSkybox":true,"showFlares":true,"showImageEffects":true,"showParticleSystems":true,"showVisualEffectGraphs":true,"m_FxEnabled":true},"in2DMode":false,"pivot":{"x":-1543.350830078125,"y":-39.60441589355469,"z":-20.95462417602539},"rotation":{"x":0.05766400694847107,"y":-0.7700086832046509,"z":0.6316320300102234,"w":0.07014857232570648},"size":91.33460998535156,"orthographic":false}